odoo/addons/account_cryptocurrency/README.rst
odoo/addons/account_cryptocurrency/__init__.py
odoo/addons/account_cryptocurrency/__manifest__.py
odoo/addons/account_cryptocurrency/data/res_currency_move_sequence.xml
odoo/addons/account_cryptocurrency/i18n/account_cryptocurrency.pot
odoo/addons/account_cryptocurrency/i18n/am.po
odoo/addons/account_cryptocurrency/i18n/ar.po
odoo/addons/account_cryptocurrency/i18n/bg.po
odoo/addons/account_cryptocurrency/i18n/bs.po
odoo/addons/account_cryptocurrency/i18n/ca.po
odoo/addons/account_cryptocurrency/i18n/ca_ES.po
odoo/addons/account_cryptocurrency/i18n/cs.po
odoo/addons/account_cryptocurrency/i18n/da.po
odoo/addons/account_cryptocurrency/i18n/de.po
odoo/addons/account_cryptocurrency/i18n/el_GR.po
odoo/addons/account_cryptocurrency/i18n/en_GB.po
odoo/addons/account_cryptocurrency/i18n/es.po
odoo/addons/account_cryptocurrency/i18n/es_AR.po
odoo/addons/account_cryptocurrency/i18n/es_CL.po
odoo/addons/account_cryptocurrency/i18n/es_CO.po
odoo/addons/account_cryptocurrency/i18n/es_CR.po
odoo/addons/account_cryptocurrency/i18n/es_DO.po
odoo/addons/account_cryptocurrency/i18n/es_EC.po
odoo/addons/account_cryptocurrency/i18n/es_ES.po
odoo/addons/account_cryptocurrency/i18n/es_MX.po
odoo/addons/account_cryptocurrency/i18n/es_PE.po
odoo/addons/account_cryptocurrency/i18n/es_PY.po
odoo/addons/account_cryptocurrency/i18n/es_VE.po
odoo/addons/account_cryptocurrency/i18n/et.po
odoo/addons/account_cryptocurrency/i18n/eu.po
odoo/addons/account_cryptocurrency/i18n/fa.po
odoo/addons/account_cryptocurrency/i18n/fi.po
odoo/addons/account_cryptocurrency/i18n/fr.po
odoo/addons/account_cryptocurrency/i18n/fr_CA.po
odoo/addons/account_cryptocurrency/i18n/fr_CH.po
odoo/addons/account_cryptocurrency/i18n/gl.po
odoo/addons/account_cryptocurrency/i18n/gl_ES.po
odoo/addons/account_cryptocurrency/i18n/gu.po
odoo/addons/account_cryptocurrency/i18n/he.po
odoo/addons/account_cryptocurrency/i18n/hr.po
odoo/addons/account_cryptocurrency/i18n/hr_HR.po
odoo14_addon_account_cryptocurrency-14.0.1.0.2.dist-info/METADATA
odoo14_addon_account_cryptocurrency-14.0.1.0.2.dist-info/WHEEL
odoo14_addon_account_cryptocurrency-14.0.1.0.2.dist-info/top_level.txt
odoo14_addon_account_cryptocurrency-14.0.1.0.2.dist-info/RECORD
